CHANGES.txt
DEPENDENCES.txt
README.txt
TODO.txt
setup.py
src/ng/__init__.py
src/ng.app.converter.egg-info/PKG-INFO
src/ng.app.converter.egg-info/SOURCES.txt
src/ng.app.converter.egg-info/dependency_links.txt
src/ng.app.converter.egg-info/namespace_packages.txt
src/ng.app.converter.egg-info/not-zip-safe
src/ng.app.converter.egg-info/requires.txt
src/ng.app.converter.egg-info/top_level.txt
src/ng/app/__init__.py
src/ng/app/converter/TODO.txt
src/ng/app/converter/__init__.py
src/ng/app/converter/configure.zcml
src/ng/app/converter/convertervocabulary.py
src/ng/app/converter/ng.app.converter.txt
src/ng/app/converter/cachehandler/__init__.py
src/ng/app/converter/cachehandler/cachehandler.py
src/ng/app/converter/cachehandler/cachehandler.txt
src/ng/app/converter/cachehandler/configure.zcml
src/ng/app/converter/cachehandler/interfaces.py
src/ng/app/converter/cachehandler/demo/__init__.py
src/ng/app/converter/cachehandler/demo/configure.zcml
src/ng/app/converter/cachehandler/demo/etc/cachehandler-demo-configure.zcml
src/ng/app/converter/cachestore/__init__.py
src/ng/app/converter/cachestore/cachestore.py
src/ng/app/converter/cachestore/cachestore.txt
src/ng/app/converter/cachestore/configure.zcml
src/ng/app/converter/cachestore/interfaces.py
src/ng/app/converter/cachestore/browser/__init__.py
src/ng/app/converter/cachestore/browser/configure.zcml
src/ng/app/converter/cachestore/browser/statistic.pt
src/ng/app/converter/cachestore/browser/statistic.py
src/ng/app/converter/cachestoreitem/__init__.py
src/ng/app/converter/cachestoreitem/cachestoreitem.py
src/ng/app/converter/cachestoreitem/cachestoreitem.txt
src/ng/app/converter/cachestoreitem/configure.zcml
src/ng/app/converter/cachestoreitem/interfaces.py
src/ng/app/converter/cachestoreitem/browser/__init__.py
src/ng/app/converter/cachestoreitem/browser/configure.zcml
src/ng/app/converter/convertadapterzcml/__init__.py
src/ng/app/converter/convertadapterzcml/configure.zcml
src/ng/app/converter/convertadapterzcml/convertadapter.py
src/ng/app/converter/convertadapterzcml/converteradapterzcml.txt
src/ng/app/converter/convertadapterzcml/meta.zcml
src/ng/app/converter/convertadapterzcml/metaconfigure.py
src/ng/app/converter/convertadapterzcml/metadirectives.py
src/ng/app/converter/converter/__init__.py
